chatgpt_test_generator/__init__.py
chatgpt_test_generator/context.py
chatgpt_test_generator/env_operations.py
chatgpt_test_generator/expression_search.py
chatgpt_test_generator/interaction.py
chatgpt_test_generator-0.1.2.dist-info/METADATA
chatgpt_test_generator-0.1.2.dist-info/LICENSE.txt
chatgpt_test_generator-0.1.2.dist-info/WHEEL
chatgpt_test_generator-0.1.2.dist-info/RECORD
